maltpynt/__init__.py
maltpynt/_astropy_init.py
maltpynt/base.py
maltpynt/calibrate.py
maltpynt/conftest.py
maltpynt/create_gti.py
maltpynt/exposure.py
maltpynt/fake.py
maltpynt/fspec.py
maltpynt/io.py
maltpynt/lags.py
maltpynt/lcurve.py
maltpynt/plot.py
maltpynt/read_events.py
maltpynt/rebin.py
maltpynt/save_as_xspec.py
maltpynt/sum_fspec.py
maltpynt/version.py
maltpynt/tests/__init__.py
maltpynt/tests/coveragerc
maltpynt/tests/setup_package.py
maltpynt/tests/test_fullrun.py
maltpynt/tests/test_unit.py
maltpynt/tests/data/FPMAmonol_test_joinlc.nc
maltpynt/tests/data/FPMBmonol_test_joinlc.nc
maltpynt/tests/data/MPcreategti.log
maltpynt/tests/data/lcurveA.fits
maltpynt/tests/data/lcurveA_lc.nc
maltpynt/tests/data/lcurve_ftools_lc.nc
maltpynt/tests/data/lcurve_ftools_pds.nc
maltpynt/tests/data/lcurve_lc.nc
maltpynt/tests/data/lcurve_txt_lc.nc
maltpynt/tests/data/lcurve_txt_lc.txt
maltpynt/tests/data/lcurve_txt_pds.nc
maltpynt/tests/data/monol_testA.evt
maltpynt/tests/data/monol_testA_E3-50_corr_lc.png
maltpynt/tests/data/monol_testA_E3-50_deadt_distr.png
maltpynt/tests/data/monol_testA_E3-50_gti.nc
maltpynt/tests/data/monol_testA_E3-50_lc.nc
maltpynt/tests/data/monol_testA_E3-50_lc_gtifilt.nc
maltpynt/tests/data/monol_testA_E3-50_lc_rebin2.nc
maltpynt/tests/data/monol_testA_E3-50_lc_rebin2_gtifilt.nc
maltpynt/tests/data/monol_testA_E3-50_lc_rebin4.nc
maltpynt/tests/data/monol_testA_E3-50_lc_rebin4_gtifilt.nc
maltpynt/tests/data/monol_testA_E3-50_pds.nc
maltpynt/tests/data/monol_testA_E3-50_pds_dumped_pds.txt
maltpynt/tests/data/monol_testA_E3-50_pds_rebin1.03.nc
maltpynt/tests/data/monol_testA_E3-50_pds_rebin1.03_xsp.dat
maltpynt/tests/data/monol_testA_E3-50_pds_rebin2.nc
maltpynt/tests/data/monol_testA_E3-50_pds_rebin2_xsp.dat
maltpynt/tests/data/monol_testA_E3-50_rebin2_gti.nc
maltpynt/tests/data/monol_testA_E3-50_rebin4_gti.nc
maltpynt/tests/data/monol_testA_PI10-300_lc.nc
maltpynt/tests/data/monol_testA_ev.nc
maltpynt-2.0a2.dist-info/DESCRIPTION.rst
maltpynt-2.0a2.dist-info/METADATA
maltpynt-2.0a2.dist-info/RECORD
maltpynt-2.0a2.dist-info/WHEEL
maltpynt-2.0a2.dist-info/entry_points.txt
maltpynt-2.0a2.dist-info/metadata.json
maltpynt-2.0a2.dist-info/pbr.json
maltpynt-2.0a2.dist-info/top_level.txt
