Metadata-Version: 2.0
Name: maltpynt
Version: 2.0a2
Summary: "Matteo's library and tools in Python for NuSTAR timing"
Home-page: https://bitbucket.org/mbachett/maltpynt
Author: Matteo Bachetti
Author-email: matteo@matteobachetti.it
License: BSD
Platform: UNKNOWN
Requires-Dist: astropy
Requires-Dist: matplotlib
Requires-Dist: numpy
Requires-Dist: scipy
